{
    "timestamp": 1605986493.86766,
    "articles": [
        {
            "title": "NJ COVID Numbers Peak Again / Nurses 'Terrified' / Travel Rules",
            "description": "NJ COVID Numbers Peak Again / Nurses 'Terrified' / Travel Rules - Point Pleasant, NJ - Check out the top news that made headlines this week across the Patch network in New Jersey.",
            "content": "Check out the top news that made headlines this week across the Patch network in New Jersey:\nGov. Murphy says coronavirus prediction models indicate cases could double if precautions aren't taken on Thanksgiving. New cases reached a daily high again ... [1656 chars]",
            "url": "https://patch.com/new-jersey/pointpleasant/nj-covid-numbers-peak-again-nurses-terrified-travel-rules",
            "image": "https://patch.com/img/cdn20/users/65079/20201121/122434/styles/patch_image/public/weekinreview-12___21122412780.jpg",
            "publishedAt": "2020-11-21T17:59:57Z",
            "source": {
                "name": "Joliet, IL Patch",
                "url": "https://patch.com/"
            }
        },
        {
            "title": "Buzz Aldrin's New Jersey childhood home is for sale",
            "description": "Long before Buzz Aldrin walked on the moon, the legendary Apollo 11 astronaut would stroll along the roof of his boyhood home in tony Montclair, NJ., gazing at the sky.",
            "content": "Jessie Buttafuoco is driven to take back her life \u2014...\nBuzz Aldrin stands in front of his childhood home in Montclair, NJ, left.\nYou\u2019ll be over the moon for this house.\nLong before Buzz Aldrin walked on the moon, the legendary Apollo 11 astronaut wou... [2669 chars]",
            "url": "https://nypost.com/2020/11/21/buzz-aldrins-new-jersey-childhood-home-is-for-sale/",
            "image": "https://nypost.com/wp-content/uploads/sites/2/2020/11/buzz-aldrin-house-moon-e1605981004611.jpg?quality=90&strip=all&w=1200",
            "publishedAt": "2020-11-21T17:55:48Z",
            "source": {
                "name": "New York Post",
                "url": "https://nypost.com/"
            }
        },
        {
            "title": "Dallas Stars unveil 'Blackout' alternate jersey",
            "description": "The Dallas Stars unveiled a new Blackout alternate uniform for the upcoming season.",
            "content": "article\nAs Dallas Stars fans are still thinking about the team\u2019s run to the Stanley Cup Final, they were given a treat Wednesday, as the Stars unveiled a new Blackout alternate uniform for the upcoming season.\nThis will be the first time since 2006 t... [1101 chars]",
            "url": "https://www.fox4news.com/sports/dallas-stars-unveil-blackout-alternate-jersey",
            "image": "https://images.foxtv.com/static.fox4news.com/www.fox4news.com/content/uploads/2020/10/1280/720/1028starsblackout.jpg?ve=1&tl=1",
            "publishedAt": "2020-11-21T06:48:48Z",
            "source": {
                "name": "FOX 4 News",
                "url": "https://www.fox4news.com/"
            }
        },
        {
            "title": "Oilersnation Radio Episode 113 - Prospect watch, Reverse Retros, and Lali Toor from APNA Hockey",
            "description": "It\u2019s Friday afternoon and that means a brand new episode of Oilersnation Radio has been recorded, edited into a masterpiece, and ready to get you set for the weekend. This week, we looked at which Oilers prospects have us most excited, Reverse Retro jersey winners and losers, spoke to Lali Toor from APNA Hockey about winning the Willie O\u2019Ree Community Hero Award, and a whole lot more.",
            "content": "It\u2019s Friday afternoon and that means a brand new episode of Oilersnation Radio has been recorded, edited into a masterpiece, and ready to get you set for the weekend. This week, we looked at which Oilers prospects have us most excited, Reverse Retro ... [1827 chars]",
            "url": "https://oilersnation.com/2020/11/20/oilersnation-radio-episode-113-and-lali-toor-from-apna-hockey/",
            "image": "https://i2.wp.com/oilersnation.com/wp-content/uploads/2020/10/Oilersnation-Radio-Updated.jpg?fit=948%2C638&ssl=1",
            "publishedAt": "2020-11-20T23:00:12Z",
            "source": {
                "name": "Oilers Nation",
                "url": "https://oilersnation.com/"
            }
        },
        {
            "title": "New Jersey man stole $90,000 before killing his brother and family, lawsuit says",
            "description": "A New Jersey man charged with murdering four members of his family is accused of stealing $90,000 prior to their November 2018 deaths, according to a newly filed wrongful death lawsuit.",
            "content": "A New Jersey man charged with murdering four members of his family is accused of stealing $90,000 prior to their November 2018 deaths, according to a newly filed wrongful death lawsuit.\nPaul Caneiro was indicted on multiple charges including four cou... [2619 chars]",
            "url": "https://www.nbcnews.com/news/us-news/new-jersey-man-stole-90-000-killing-his-brother-family-n1248452",
            "image": "https://media3.s-nbcnews.com/j/newscms/2020_47/2789936/190318-paul-caneiro-cs-150a_616948ff99c941f3689d5069c0dce50d.nbcnews-fp-1200-630.jpg",
            "publishedAt": "2020-11-20T22:43:00Z",
            "source": {
                "name": "NBC News",
                "url": "https://www.nbcnews.com/"
            }
        }
    ]
}